sheval/__init__.py
sheval-1.1.0.post1.dist-info/LICENSE
sheval-1.1.0.post1.dist-info/METADATA
sheval-1.1.0.post1.dist-info/WHEEL
sheval-1.1.0.post1.dist-info/RECORD
