Metadata-Version: 2.1
Name: sheval
Version: 1.1.0.post1
Summary: Safely evaluate mathematical and logical expressions.
Home-page: https://gitlab.com/deepadmax/sheval
License: GPL-3.0-or-later
Author: Maximillian Strand
Author-email: maxi@millian.se
Requires-Python: >=3.10,<4.0
Classifier: License :: OSI Approved :: GNU General Public License v3 or later (GPLv3+)
Classifier: Programming Language :: Python :: 3
Classifier: Programming Language :: Python :: 3.10
Classifier: Programming Language :: Python :: 3.11
Classifier: Programming Language :: Python :: 3.12
Project-URL: Repository, https://gitlab.com/deepadmax/sheval
